nonebot_plugin_fortune/__init__.py
nonebot_plugin_fortune/config.py
nonebot_plugin_fortune/data_source.py
nonebot_plugin_fortune/download.py
nonebot_plugin_fortune/resource/font/Mamelon.otf
nonebot_plugin_fortune/resource/font/sakura.ttf
nonebot_plugin_fortune/resource/fortune/copywriting.json
nonebot_plugin_fortune/resource/fortune_data.json
nonebot_plugin_fortune/resource/fortune_setting.json
nonebot_plugin_fortune/utils.py
nonebot_plugin_fortune-0.4.6.dist-info/LICENSE
nonebot_plugin_fortune-0.4.6.dist-info/WHEEL
nonebot_plugin_fortune-0.4.6.dist-info/METADATA
nonebot_plugin_fortune-0.4.6.dist-info/RECORD
