Metadata-Version: 2.1
Name: nonebot-plugin-fortune
Version: 0.4.6
Summary: Fortune divination!
License: MIT
Author: KafCoppelia
Author-email: k740677208@gmail.com
Requires-Python: >=3.7.3,<4.0.0
Classifier: License :: OSI Approved :: MIT License
Classifier: Programming Language :: Python :: 3
Classifier: Programming Language :: Python :: 3.10
Classifier: Programming Language :: Python :: 3.8
Classifier: Programming Language :: Python :: 3.9
Requires-Dist: httpx (>=0.23.0,<0.24.0)
Requires-Dist: nonebot-adapter-onebot (>=2.1.1,<3.0.0)
Requires-Dist: nonebot-plugin-apscheduler (>=0.1.3,<0.2.0)
Requires-Dist: nonebot2 (>=2.0.0b3,<3.0.0)
Requires-Dist: pillow (>=9.0.0,<10.0.0)
Requires-Dist: ujson (>=5.1.0,<6.0.0)
